{
  "item_ID": {
    "0": 1,
    "1": 2,
    "2": 3,
    "3": 4,
    "4": 5,
    "5": 6,
    "6": 7,
    "7": 8,
    "8": 9,
    "9": 10,
    "10": 11,
    "11": 12,
    "12": 13,
    "13": 14,
    "14": 15,
    "15": 16,
    "16": 17,
    "17": 18,
    "18": 19,
    "19": 20,
    "20": 21,
    "21": 22,
    "22": 23,
    "23": 24,
    "24": 25,
    "25": 26,
    "26": 27,
    "27": 28,
    "28": 29,
    "29": 30,
    "30": 31,
    "31": 32,
    "32": 33,
    "33": 34,
    "34": 35,
    "35": 36,
    "36": 37,
    "37": 38,
    "38": 39,
    "39": 40,
    "40": 41,
    "41": 42,
    "42": 43,
    "43": 44,
    "44": 45,
    "45": 46,
    "46": 47,
    "47": 48,
    "48": 49,
    "49": 50,
    "50": 51,
    "51": 52,
    "52": 53,
    "53": 54,
    "54": 55,
    "55": 56,
    "56": 57,
    "57": 58,
    "58": 59,
    "59": 60,
    "60": 61,
    "61": 62,
    "62": 63,
    "63": 64,
    "64": 65,
    "65": 66,
    "66": 67,
    "67": 68,
    "68": 69,
    "69": 70,
    "70": 71,
    "71": 72,
    "72": 73,
    "73": 74,
    "74": 75,
    "75": 76,
    "76": 77,
    "77": 78,
    "78": 79,
    "79": 81,
    "80": 86,
    "81": 89,
    "82": 90,
    "83": 91,
    "84": 92,
    "85": 95,
    "86": 96,
    "87": 97,
    "88": 98,
    "89": 99,
    "90": 100,
    "91": 101,
    "92": 102,
    "93": 103,
    "94": 104,
    "95": 105,
    "96": 106
  },
  "Name": {
    "0": "801 MM Kit",
    "1": "801 Audio Kit",
    "2": "802 MM Kit",
    "3": "802 Audio Kit",
    "4": "HopeKids Ipad 1",
    "5": "Type C HDMI 1",
    "6": "Type C HDMI 2",
    "7": "Walkie-1",
    "8": "Walkie-2",
    "9": "Walkie-3",
    "10": "Walkie-4",
    "11": "Walkie-5",
    "12": "Walkie-6",
    "13": "Walkie-7",
    "14": "Walkie-8",
    "15": "Walkie-9",
    "16": "Walkie-10",
    "17": "Walkie-11",
    "18": "Walkie-12",
    "19": "Walkie-13",
    "20": "Walkie-14",
    "21": "Walkie-15",
    "22": "Walkie-16",
    "23": "Walkie-17",
    "24": "Walkie-18",
    "25": "Walkie-19",
    "26": "Walkie-20",
    "27": "Walkie-21",
    "28": "Walkie-22",
    "29": "Walkie-23",
    "30": "Walkie-24",
    "31": "Walkie-25",
    "32": "Walkie-26",
    "33": "Walkie-27",
    "34": "Walkie-28",
    "35": "Walkie-29",
    "36": "Walkie-30",
    "37": "Deposit Room Key",
    "38": "Comm Key",
    "39": "Entrance TV Key",
    "40": "Foyer 1 Key",
    "41": "Foyer 2 Key",
    "42": "Foyer 3 Key",
    "43": "Empty Key 1",
    "44": "Empty Key 2",
    "45": "Kids Ark Key",
    "46": "Empty Key 3",
    "47": "Hope Kids Key",
    "48": "Hope Kids Filipino Key",
    "49": "Hope Kids Bilingual Key",
    "50": "Hope Kids Stationery Key",
    "51": "HK Check In 01 Key",
    "52": "Usher Key",
    "53": "Shine Cabinet Key",
    "54": "Shine Key",
    "55": "Dialect Key",
    "56": "Prayer Cabinet Key",
    "57": "Finance RM Key",
    "58": "Facilities Cabinet 1 Key",
    "59": "Facilities Cabinet 2 Key",
    "60": "Level 1 TV Key",
    "61": "KG CCTV Key",
    "62": "West Keys",
    "63": "Empty Key 4",
    "64": "Empty Key 5",
    "65": "Empty Key 6",
    "66": "Empty Key 7",
    "67": "In Ear Monitor 801",
    "68": "In Ear Monitor 802",
    "69": "In Ear Monitor 806",
    "70": "Whiteboard Marker 801",
    "71": "Whiteboard Marker 802",
    "72": "Whiteboard Marker 806",
    "73": "Whiteboard Marker 807",
    "74": "Whiteboard Marker 803",
    "75": "Whiteboard Marker 804",
    "76": "Whiteboard Marker 805",
    "77": "Whiteboard Marker 701",
    "78": "Whiteboard Marker 702",
    "79": "HDMI Cable",
    "80": "401 Access Card",
    "81": "Shure Mic SM57",
    "82": "HopeKids Ipad 2",
    "83": "Security TL Access card",
    "84": "C806 HSM1",
    "85": "CT Hub Access Card",
    "86": "Ablaze Offerings Bag",
    "87": "701 HDMI dongle",
    "88": "702 HDMI Dongle",
    "89": "Cooler Box 1",
    "90": "Cooler Box 2",
    "91": "Level 8 access key",
    "92": "Key 40: Tithing Box Key (Hopekids)",
    "93": "Connect 8 HK Keys",
    "94": "Connect 8 Facilities Storage ",
    "95": "Extension Plug",
    "96": "Loud Hailer"
  },
  "category": {
    "0": "Visual",
    "1": "Audio",
    "2": "Visual",
    "3": "Audio",
    "4": "Hopekids",
    "5": "Peripheral",
    "6": "Peripheral",
    "7": "Walkie Talkie",
    "8": "Walkie Talkie",
    "9": "Walkie Talkie",
    "10": "Walkie Talkie",
    "11": "Walkie Talkie",
    "12": "Walkie Talkie",
    "13": "Walkie Talkie",
    "14": "Walkie Talkie",
    "15": "Walkie Talkie",
    "16": "Walkie Talkie",
    "17": "Walkie Talkie",
    "18": "Walkie Talkie",
    "19": "Walkie Talkie",
    "20": "Walkie Talkie",
    "21": "Walkie Talkie",
    "22": "Walkie Talkie",
    "23": "Walkie Talkie",
    "24": "Walkie Talkie",
    "25": "Walkie Talkie",
    "26": "Walkie Talkie",
    "27": "Walkie Talkie",
    "28": "Walkie Talkie",
    "29": "Walkie Talkie",
    "30": "Walkie Talkie",
    "31": "Walkie Talkie",
    "32": "Walkie Talkie",
    "33": "Walkie Talkie",
    "34": "Walkie Talkie",
    "35": "Walkie Talkie",
    "36": "Walkie Talkie",
    "37": "Key-closet2-1",
    "38": "Key-closet2-2",
    "39": "Key-closet2-3",
    "40": "Key-closet2-4",
    "41": "Key-closet2-5",
    "42": "Key-closet2-6",
    "43": "Key-closet2-7",
    "44": "Key-closet2-8",
    "45": "Key-closet2-9",
    "46": "Key-closet2-10",
    "47": "Key-closet2-11",
    "48": "Key-closet2-12",
    "49": "Key-closet2-13",
    "50": "Key-closet2-14",
    "51": "Key-closet2-15",
    "52": "Key-closet2-16",
    "53": "Key-closet2-17",
    "54": "Key-closet2-18",
    "55": "Key-closet2-19",
    "56": "Key-closet2-20",
    "57": "Key-closet2-21",
    "58": "Key-closet2-22",
    "59": "Key-closet2-23",
    "60": "Key-closet2-24",
    "61": "Key-closet2-25",
    "62": "Key-closet2-26",
    "63": "Key-closet2-27",
    "64": "Key-closet2-28",
    "65": "Key-closet2-29",
    "66": "Key-closet2-30",
    "67": "In Ear Monitor",
    "68": "In Ear Monitor",
    "69": "In Ear Monitor",
    "70": "Whiteboard Marker",
    "71": "Whiteboard Marker",
    "72": "Whiteboard Marker",
    "73": "Whiteboard Marker",
    "74": "Whiteboard Marker",
    "75": "Whiteboard Marker",
    "76": "Whiteboard Marker",
    "77": "Whiteboard Marker",
    "78": "Whiteboard Marker",
    "79": "Visual",
    "80": "Security",
    "81": "Audio",
    "82": "Hopekids",
    "83": null,
    "84": null,
    "85": "Access Card",
    "86": null,
    "87": null,
    "88": null,
    "89": null,
    "90": null,
    "91": null,
    "92": null,
    "93": "Keys",
    "94": "Facilities ",
    "95": null,
    "96": null
  },
  "description": {
    "0": null,
    "1": null,
    "2": null,
    "3": null,
    "4": null,
    "5": null,
    "6": null,
    "7": null,
    "8": null,
    "9": null,
    "10": null,
    "11": null,
    "12": null,
    "13": null,
    "14": null,
    "15": null,
    "16": null,
    "17": null,
    "18": null,
    "19": null,
    "20": null,
    "21": null,
    "22": null,
    "23": null,
    "24": null,
    "25": null,
    "26": null,
    "27": null,
    "28": null,
    "29": null,
    "30": null,
    "31": null,
    "32": null,
    "33": null,
    "34": null,
    "35": null,
    "36": null,
    "37": null,
    "38": null,
    "39": null,
    "40": null,
    "41": null,
    "42": null,
    "43": null,
    "44": null,
    "45": null,
    "46": null,
    "47": null,
    "48": null,
    "49": null,
    "50": null,
    "51": null,
    "52": null,
    "53": null,
    "54": null,
    "55": null,
    "56": null,
    "57": null,
    "58": null,
    "59": null,
    "60": null,
    "61": null,
    "62": null,
    "63": null,
    "64": null,
    "65": null,
    "66": null,
    "67": null,
    "68": null,
    "69": null,
    "70": null,
    "71": null,
    "72": null,
    "73": null,
    "74": null,
    "75": null,
    "76": null,
    "77": null,
    "78": null,
    "79": null,
    "80": null,
    "81": "Sm57",
    "82": null,
    "83": "Security team",
    "84": null,
    "85": null,
    "86": null,
    "87": null,
    "88": null,
    "89": null,
    "90": null,
    "91": null,
    "92": null,
    "93": "Keys",
    "94": "L8 Storage Key",
    "95": null,
    "96": null
  }
}
